cli_table/__init__.py
cli_table/aligners.py
cli_table/table.py
cli_table/util.py
hamolicious_cli_table-1.1.1.dist-info/LICENCE
hamolicious_cli_table-1.1.1.dist-info/METADATA
hamolicious_cli_table-1.1.1.dist-info/WHEEL
hamolicious_cli_table-1.1.1.dist-info/top_level.txt
hamolicious_cli_table-1.1.1.dist-info/RECORD
